LICENSE
MANIFEST.in
README.md
setup.py
tunel/__init__.py
tunel/__main__.py
tunel/config.py
tunel/config_dummy.py
tunel/logman.py
tunel/server.py
tunel/utils.py
tunel/version.py
tunel/wsgi.py
tunel.egg-info/PKG-INFO
tunel.egg-info/SOURCES.txt
tunel.egg-info/dependency_links.txt
tunel.egg-info/entry_points.txt
tunel.egg-info/not-zip-safe
tunel.egg-info/requires.txt
tunel.egg-info/top_level.txt
tunel/static/css/bootstrap.min.css
tunel/static/css/datatables.min.css
tunel/static/css/fonts.min.css
tunel/static/css/generator.css
tunel/static/css/mobile-base-1.1.css
tunel/static/css/select2.min.css
tunel/static/css/skeleton.css
tunel/static/css/style.css
tunel/static/css/fonts/Montserrat-Black.eot
tunel/static/css/fonts/Montserrat-Black.svg
tunel/static/css/fonts/Montserrat-Black.ttf
tunel/static/css/fonts/Montserrat-Black.woff
tunel/static/css/fonts/Montserrat-Bold.eot
tunel/static/css/fonts/Montserrat-Bold.svg
tunel/static/css/fonts/Montserrat-Bold.ttf
tunel/static/css/fonts/Montserrat-Bold.woff
tunel/static/css/fonts/Montserrat-Light.eot
tunel/static/css/fonts/Montserrat-Light.svg
tunel/static/css/fonts/Montserrat-Light.ttf
tunel/static/css/fonts/Montserrat-Light.woff
tunel/static/css/fonts/Montserrat-Regular.eot
tunel/static/css/fonts/Montserrat-Regular.svg
tunel/static/css/fonts/Montserrat-Regular.ttf
tunel/static/css/fonts/Montserrat-Regular.woff
tunel/static/img/about-history.jpg
tunel/static/img/about-philosophy.jpg
tunel/static/img/about-visual.png
tunel/static/img/about-winners.jpg
tunel/static/img/contact-visual.png
tunel/static/img/introduction-visual.png
tunel/static/img/logo.png
tunel/static/img/robot-blinking.png
tunel/static/img/robot.png
tunel/static/img/work-alex-nowak.jpg
tunel/static/img/work-metiew-smith.jpg
tunel/static/img/work-victory.jpg
tunel/static/js/bootstrap.min.js
tunel/static/js/datatables.min.js
tunel/static/js/generator-functions.js
tunel/static/js/jquery-3.2.1.slim.min.js
tunel/static/js/jquery.min.js
tunel/static/js/popper.min.js
tunel/static/js/select2.min.js
tunel/static/js/tipsy.js
tunel/templates/base.html
tunel/templates/bases.html
tunel/templates/basesv1.html
tunel/templates/container.html
tunel/templates/containers.html
