Metadata-Version: 1.1
Name: tunel
Version: 1.0.0
Summary: commander and viewer to tunnel commands for HPC
Home-page: http://www.github.com/vsoch/tunel
Author: Vanessa Sochat
Author-email: vsochat@stanford.edu
License: LICENSE
Keywords: commander,containers,viewer,hpc,cluster,computing
Platform: UNKNOWN
Classifier: Intended Audience :: Science/Research
Classifier: Intended Audience :: Developers
Classifier: License :: OSI Approved :: BSD License
Classifier: Programming Language :: C
Classifier: Programming Language :: Python
Classifier: Topic :: Software Development
Classifier: Topic :: Scientific/Engineering
Classifier: Operating System :: Unix
Classifier: Programming Language :: Python :: 2.7
Classifier: Programming Language :: Python :: 3
